volcano/web/__init__.py
volcano/web/__main__.py
volcano/web/www/__init__.py
volcano/web/www/alarms.js
volcano/web/www/diag.html
volcano/web/www/diag.js
volcano/web/www/favicon.ico
volcano/web/www/green_tiger.js
volcano/web/www/index.html
volcano/web/www/index.js
volcano/web/www/navbar.js
volcano/web/www/the_time.js
volcano/web/www/ext/angular/angular.min.js
volcano/web/www/ext/angular/angular.min.js.map
volcano/web/www/ext/bootstrap3/css/bootstrap-theme.min.css
volcano/web/www/ext/bootstrap3/css/bootstrap-theme.min.css.map
volcano/web/www/ext/bootstrap3/css/bootstrap.min.css
volcano/web/www/ext/bootstrap3/css/bootstrap.min.css.map
volcano/web/www/ext/bootstrap3/fonts/glyphicons-halflings-regular.eot
volcano/web/www/ext/bootstrap3/fonts/glyphicons-halflings-regular.svg
volcano/web/www/ext/bootstrap3/fonts/glyphicons-halflings-regular.ttf
volcano/web/www/ext/bootstrap3/fonts/glyphicons-halflings-regular.woff
volcano/web/www/ext/bootstrap3/fonts/glyphicons-halflings-regular.woff2
volcano/web/www/ext/bootstrap3/js/bootstrap.min.js
volcano/web/www/ext/bootstrap3/js/npm.js
volcano/web/www/ext/jquery/jquery.js
volcano_web-1.5.5.dist-info/LICENSE
volcano_web-1.5.5.dist-info/METADATA
volcano_web-1.5.5.dist-info/WHEEL
volcano_web-1.5.5.dist-info/top_level.txt
volcano_web-1.5.5.dist-info/RECORD
